unexart_lib/__init__.py
unexart_lib/bubblesort.py
unexart_lib/calculator.py
unexart_lib/fibonacci.py
unexart_lib-0.0.1.dist-info/METADATA
unexart_lib-0.0.1.dist-info/WHEEL
unexart_lib-0.0.1.dist-info/top_level.txt
unexart_lib-0.0.1.dist-info/RECORD
