Metadata-Version: 2.1
Name: unexart-lib
Version: 0.0.1
Summary: This is the simplest module created for educational purposes.
Home-page: https://github.com/UnexarT/unexart_lib
Author: unexart
Author-email: unexart4132@gmail.com
Project-URL: GitHub, https://github.com/UnexarT/unexart_lib
Keywords: Fibonacci bubblesort calculator
Classifier: Programming Language :: Python :: 3.9
Classifier: License :: OSI Approved :: MIT License
Classifier: Operating System :: OS Independent
Requires-Python: >=3.6
Requires-Dist: requests >=2.25.1
